HISTORY.rst
LICENSE
MANIFEST.in
README.rst
requirements-tests.txt
requirements.txt
setup.py
protobuf_gen/__init__.py
protobuf_gen/abstract.py
protobuf_gen/const.py
protobuf_gen/error.py
protobuf_gen/main.py
protobuf_gen/patch.py
protobuf_gen/remap.py
protobuf_gen/transpiler.py
protobuf_gen/wrap.py
protobuf_gen.egg-info/PKG-INFO
protobuf_gen.egg-info/SOURCES.txt
protobuf_gen.egg-info/dependency_links.txt
protobuf_gen.egg-info/requires.txt
protobuf_gen.egg-info/top_level.txt
protobuf_gen/autogen/__init__.py
protobuf_gen/autogen/core.py
protobuf_gen/reflection/__init__.py
protobuf_gen/reflection/generate_pb_core.py