Metadata-Version: 1.1
Name: protobuf-gen
Version: 0.0.2
Summary: Python 3 type hinted protobuf binding generator
Home-page: https://github.com/andreycizov/python-protobuf-gen
Author: Andrey Cizov
Author-email: acizov@gmail.com
License: UNKNOWN
Platform: UNKNOWN
Classifier: Development Status :: 2 - Pre-Alpha
Classifier: Intended Audience :: Developers
Classifier: License :: OSI Approved :: Apache Software License
Classifier: Natural Language :: English
Classifier: Programming Language :: Python :: 3.6
